Metadata-Version: 2.1
Name: signalfx-instrumentation-redis
Version: 1.0.0
Summary: OpenTracing support for Redis
Home-page: https://github.com/signalfx/python-redis/
Author: SignalFx, Inc.
Author-email: signalfx-oss@splunk.com
License: Apache License 2.0
Download-URL: https://github.com/signalfx/python-redis/tarball/1.0.0
Platform: any
Classifier: Intended Audience :: Developers
Classifier: License :: OSI Approved :: BSD License
Classifier: Operating System :: OS Independent
Classifier: Programming Language :: Python
Classifier: Topic :: Software Development :: Libraries :: Python Modules
Provides-Extra: tests
